swiftagents/__init__.py
swiftagents/benchmarks/__init__.py
swiftagents/benchmarks/run_benchmark.py
swiftagents/core/__init__.py
swiftagents/core/cache.py
swiftagents/core/judge.py
swiftagents/core/metrics.py
swiftagents/core/models.py
swiftagents/core/prompts.py
swiftagents/core/router.py
swiftagents/core/scheduler.py
swiftagents/core/tools.py
swiftagents/examples/__init__.py
swiftagents/examples/function_tool_demo.py
swiftagents/examples/speculative_execution_demo.py
swiftagents/examples/tool_selection.py
swiftagents/tests/test_router.py
swiftagents/tests/test_runtime.py
swiftagents-0.1.0.dist-info/licenses/LICENSE
swiftagents-0.1.0.dist-info/METADATA
swiftagents-0.1.0.dist-info/WHEEL
swiftagents-0.1.0.dist-info/top_level.txt
swiftagents-0.1.0.dist-info/RECORD
