Metadata-Version: 2.4
Name: swiftagents
Version: 0.1.0
Summary: Superfast logprob-native agent runtime
Author: swiftagents contributors
License: Apache-2.0
Keywords: agents,llm,logprobs,async,tools
Classifier: Development Status :: 3 - Alpha
Classifier: Programming Language :: Python :: 3
Classifier: License :: OSI Approved :: Apache Software License
Requires-Python: >=3.10
License-File: LICENSE
Requires-Dist: httpx>=0.24
Requires-Dist: pydantic>=2.0
Provides-Extra: dev
Requires-Dist: pytest>=7.4; extra == "dev"
Requires-Dist: pytest-asyncio>=0.23; extra == "dev"
Dynamic: license-file
